{
  "schema_version": 1,
  "items": [
    {"abbr": "YTD",     "expansion": "Year To Date — performance from January 1 of the current year to today."},
    {"abbr": "MTD",     "expansion": "Month To Date — performance from the first of the current month to today."},
    {"abbr": "QTD",     "expansion": "Quarter To Date — performance from the first day of the current quarter."},
    {"abbr": "TTM",     "expansion": "Trailing Twelve Months — the most recent 12 months of data, rolling."},
    {"abbr": "LTM",     "expansion": "Last Twelve Months — synonym for TTM."},
    {"abbr": "FY",      "expansion": "Fiscal Year — a company's accounting year (often not Jan–Dec)."},
    {"abbr": "FQ",      "expansion": "Fiscal Quarter — a quarter within a company's fiscal year."},
    {"abbr": "MoM",     "expansion": "Month-over-Month — change vs. the prior month."},
    {"abbr": "QoQ",     "expansion": "Quarter-over-Quarter — change vs. the prior quarter."},
    {"abbr": "YoY",     "expansion": "Year-over-Year — change vs. the same period one year ago."},
    {"abbr": "WoW",     "expansion": "Week-over-Week — change vs. the prior week."},
    {"abbr": "DoD",     "expansion": "Day-over-Day — change vs. the prior trading day."},
    {"abbr": "EPS",     "expansion": "Earnings Per Share — net income divided by shares outstanding."},
    {"abbr": "P/E",     "expansion": "Price-to-Earnings ratio — share price divided by EPS."},
    {"abbr": "P/B",     "expansion": "Price-to-Book ratio — share price divided by book value per share."},
    {"abbr": "P/S",     "expansion": "Price-to-Sales ratio — market cap divided by trailing revenue."},
    {"abbr": "PEG",     "expansion": "Price/Earnings-to-Growth ratio — P/E divided by expected EPS growth rate."},
    {"abbr": "EV",      "expansion": "Enterprise Value — market cap plus debt minus cash; the cost to buy the business."},
    {"abbr": "EBITDA",  "expansion": "Earnings Before Interest, Taxes, Depreciation, and Amortization."},
    {"abbr": "EBIT",    "expansion": "Earnings Before Interest and Taxes — operating income."},
    {"abbr": "FCF",     "expansion": "Free Cash Flow — operating cash flow minus capital expenditures."},
    {"abbr": "CapEx",   "expansion": "Capital Expenditures — money spent on long-lived physical assets."},
    {"abbr": "OpEx",    "expansion": "Operating Expenses — day-to-day cost of running the business."},
    {"abbr": "COGS",    "expansion": "Cost of Goods Sold — direct cost of producing what is sold."},
    {"abbr": "ROE",     "expansion": "Return on Equity — net income divided by shareholder equity."},
    {"abbr": "ROA",     "expansion": "Return on Assets — net income divided by total assets."},
    {"abbr": "ROIC",    "expansion": "Return on Invested Capital — operating profit (after tax) divided by debt + equity."},
    {"abbr": "WACC",    "expansion": "Weighted Average Cost of Capital — blended cost of a firm's debt and equity."},
    {"abbr": "DCF",     "expansion": "Discounted Cash Flow — valuation by discounting future cash flows to today."},
    {"abbr": "NPV",     "expansion": "Net Present Value — sum of discounted future cash flows minus initial cost."},
    {"abbr": "IRR",     "expansion": "Internal Rate of Return — discount rate that makes NPV zero."},
    {"abbr": "ARR",     "expansion": "Annual Recurring Revenue — annualized run-rate of subscription revenue."},
    {"abbr": "MRR",     "expansion": "Monthly Recurring Revenue — subscription revenue normalized to a month."},
    {"abbr": "GMV",     "expansion": "Gross Merchandise Value — total dollar value of goods sold via a platform."},
    {"abbr": "ATR",     "expansion": "Average True Range — measure of volatility based on recent price ranges."},
    {"abbr": "RSI",     "expansion": "Relative Strength Index — momentum oscillator (0–100), >70 overbought / <30 oversold."},
    {"abbr": "MACD",    "expansion": "Moving Average Convergence Divergence — trend-following momentum indicator."},
    {"abbr": "VWAP",    "expansion": "Volume-Weighted Average Price — average price weighted by volume traded."},
    {"abbr": "TWAP",    "expansion": "Time-Weighted Average Price — average price over a time window."},
    {"abbr": "MA",      "expansion": "Moving Average — a smoothed average of price over N periods."},
    {"abbr": "SMA",     "expansion": "Simple Moving Average — equal-weighted MA."},
    {"abbr": "EMA",     "expansion": "Exponential Moving Average — MA that weights recent prices more heavily."},
    {"abbr": "BB",      "expansion": "Bollinger Bands — a moving average ± N standard deviations."},
    {"abbr": "OI",      "expansion": "Open Interest — number of outstanding derivatives contracts not yet closed."},
    {"abbr": "IV",      "expansion": "Implied Volatility — the volatility implied by an option's market price."},
    {"abbr": "HV",      "expansion": "Historical Volatility — realized volatility computed from past prices."},
    {"abbr": "ITM",     "expansion": "In The Money — an option with intrinsic value (would profit if exercised now)."},
    {"abbr": "OTM",     "expansion": "Out of The Money — an option with no intrinsic value at the current price."},
    {"abbr": "ATM",     "expansion": "At The Money — strike approximately equal to the underlying price."},
    {"abbr": "DTE",     "expansion": "Days To Expiration — calendar days until an option or future expires."},
    {"abbr": "VaR",     "expansion": "Value at Risk — maximum expected loss over a horizon at a given confidence."},
    {"abbr": "CVaR",    "expansion": "Conditional VaR — average loss in the worst-case tail beyond VaR."},
    {"abbr": "MDD",     "expansion": "Maximum Drawdown — largest peak-to-trough loss during a period."},
    {"abbr": "AUM",     "expansion": "Assets Under Management — total market value of assets a firm manages."},
    {"abbr": "NAV",     "expansion": "Net Asset Value — fund's total assets minus liabilities, per share."},
    {"abbr": "ETF",     "expansion": "Exchange-Traded Fund — a fund traded on an exchange like a stock."},
    {"abbr": "REIT",    "expansion": "Real Estate Investment Trust — pass-through entity that owns/finances real estate."},
    {"abbr": "IPO",     "expansion": "Initial Public Offering — first sale of shares to public markets."},
    {"abbr": "SPAC",    "expansion": "Special Purpose Acquisition Company — shell that IPOs to acquire a private firm."},
    {"abbr": "M&A",     "expansion": "Mergers and Acquisitions — transactions where companies combine or are bought."},
    {"abbr": "LBO",     "expansion": "Leveraged Buyout — acquisition financed largely with borrowed money."},
    {"abbr": "PIPE",    "expansion": "Private Investment in Public Equity — private placement of public-company shares."},
    {"abbr": "S&P 500", "expansion": "Standard & Poor's 500 — index of 500 large US-listed companies."},
    {"abbr": "DJIA",    "expansion": "Dow Jones Industrial Average — price-weighted index of 30 large US firms."},
    {"abbr": "VIX",     "expansion": "CBOE Volatility Index — 30-day implied vol of S&P 500 options ('fear index')."},
    {"abbr": "FOMC",    "expansion": "Federal Open Market Committee — sets US monetary policy."},
    {"abbr": "CPI",     "expansion": "Consumer Price Index — measure of consumer-level inflation."},
    {"abbr": "PPI",     "expansion": "Producer Price Index — measure of producer-level inflation."},
    {"abbr": "GDP",     "expansion": "Gross Domestic Product — total value of goods/services produced in a country."},
    {"abbr": "PMI",     "expansion": "Purchasing Managers' Index — survey-based gauge of business activity."},
    {"abbr": "NFP",     "expansion": "Non-Farm Payrolls — monthly US jobs report ex-agriculture."},
    {"abbr": "bps",     "expansion": "Basis Points — 1 bp = 0.01%. 100 bps = 1 percentage point."},
    {"abbr": "FX",      "expansion": "Foreign Exchange — the currency market."}
  ]
}
